Workbook

Sheet Start here
B2: Agentic AI Production Readiness Scorecard
B3: Scoring workbook · Version 1.1 · October 2026 · Nitin Gupta · Enterprise AI Decision Toolkit
B4: WORKED EXAMPLE. Every name, figure and score below is fictional and illustrative, not a benchmark.
B6: The system being scored
B7: System name | C7: Invoice-matching agent, accounts payable (fictional)
B8: Action types in scope | C8: Flag three-way matches for clerk approval
B9: Assessment date | C9: 2026-03-31
B10: Facilitator (not on the build team) | C10: Internal audit lead (not on the build team)
B11: Authority the system holds today | C11: Recommend
B13: How to use this workbook
B14: 1. Score one system | C14: Score one agentic AI system as it runs today. Do not score plans, roadmaps or work in progress.
B15: 2. Enter scores | C15: On the Scorecard sheet, enter 0, 1, 2 or 3 in the yellow Score column for all 37 criteria. Record the evidence shown and where it lives.
B16: 3. Read the result | C16: The Summary sheet totals the score, applies the six gates, names the readiness band and the maximum authority state, and compares it with the authority the system holds today.
B17: 4. Act on the gap | C17: If the system holds more authority than its band allows, the authority owner restricts it now or accepts the gap in writing within one week.
B19: Scoring rules
B20: No evidence, no points | C20: Every score above 0 must be backed by something the team can show in the room. "We do that" without evidence scores 0.
B21: Lowest true anchor | C21: Award the highest anchor where every condition is true. Anchors are cumulative: a 3 requires everything in the 2.
B22: When in doubt, score lower | C22: Disagreements that evidence cannot settle are scored at the lower value and logged as an action.
B23: Gates cap the band | C23: Six criteria are gates. They add no points, but they cap the readiness band whatever the total.
B25: Legend
B26: Yellow cells | C26: Inputs. Everything else is calculated or reference text.
B27: Rose rows | C27: Gate criteria.
B29: The written scorecard (SCORECARD.md) is the authority. If this workbook and the written scorecard ever disagree, the written scorecard wins. No macros. Not a certification, a legal opinion or a compliance program.
B31: github.com/ngupta1137/enterprise-ai-decision-toolkit · doi.org/10.5281/zenodo.23464328 · MIT license

Sheet Scorecard
A1: Scorecard: enter one score per criterion in the yellow column. Evidence or zero.
A3: ID | B3: Category | C3: Criterion | D3: Gate | E3: What it tests | F3: Anchor 0 | G3: Anchor 1 | H3: Anchor 2 | I3: Anchor 3 | J3: Score (0-3) | K3: Maturity level | L3: Evidence shown | M3: Where the evidence lives | N3: Action, owner, date
A4: 1.1 | B4: 1. Authorization and Decision Rights | C4: Written authority boundary | D4: GATE | E4: The system's permitted actions are written down: every system it can write to, every action type it can take, and numeric limits on those actions. | F4: No written list of permitted actions exists. | G4: A written description exists, but it has no numeric limits (value, volume, or record count), or it omits at least one system the agent can write to. | H4: The written list covers every system the agent can write to, every action type, and numeric limits for each, and the accountable decision owner (1.2) has approved it. | I4: As 2, and the limits are enforced in code or platform configuration, and the document is version-controlled with dated changes. | J4: 2 | K4: =IF(J4="","",CHOOSE(J4+1,"1 - Ad hoc","2 - Developing","3 - Defined","4 - Managed")) -> 3 - Defined | L4: Signed boundary: match flags only, invoices under $5,000, one finance instance | M4: Governance site / AP-agent / boundary v3
A5: 1.2 | B5: 1. Authorization and Decision Rights | C5: Named authority owner | D5: GATE | E5: One named individual holds the right to approve, expand, restrict, or revoke this system's authority. | F5: No one is named, or the answer depends on who is asked. | G5: A team or committee is named, but no single individual. | H5: A named individual is recorded as holding that right, and the record states all four powers: approve, expand, restrict, revoke. | I5: As 2, and a named backup exists, and both are listed in an enterprise governance register or AI inventory. | J5: 2 | K5: =IF(J5="","",CHOOSE(J5+1,"1 - Ad hoc","2 - Developing","3 - Defined","4 - Managed")) -> 3 - Defined | L5: AP controller named with approve, expand, restrict, revoke | M5: Authority register entry AP-01 | N5: Name a backup (owner: AP controller, by 30 Apr)
A6: 1.3 | B6: 1. Authorization and Decision Rights | C6: Current authority state recorded | E6: The system's authority is recorded as one of five states for each action type: observe, recommend, act with approval, bounded autonomy, expanded autonomy. | F6: No authority state is recorded. | G6: One label is recorded for the whole system, regardless of action type. | H6: A state is recorded for each action type the system can take. | I6: As 2, and states are recorded separately for each market or business unit where they differ, with the date each state last changed. | J6: 2 | K6: =IF(J6="","",CHOOSE(J6+1,"1 - Ad hoc","2 - Developing","3 - Defined","4 - Managed")) -> 3 - Defined | L6: State recorded per action type | M6: Agent register
A7: 1.4 | B7: 1. Authorization and Decision Rights | C7: Promotion criteria set in advance | E7: The evidence required to move to a higher authority state was written down before the current state was granted. | F7: No promotion criteria exist. | G7: Criteria are described in words with no measurable thresholds, or were written after the promotion. | H7: Measurable thresholds and a minimum volume of evidence were written down before the current authority state was granted. | I7: As 2, and the most recent promotion decision is recorded with the actual evidence compared against those thresholds. | J7: 2 | K7: =IF(J7="","",CHOOSE(J7+1,"1 - Ad hoc","2 - Developing","3 - Defined","4 - Managed")) -> 3 - Defined | L7: Thresholds written before Recommend was granted: 98% agreement on 1,000+ invoices | M7: Authority Change Record AP-001
A8: 1.5 | B8: 1. Authorization and Decision Rights | C8: Demotion and revocation triggers | D8: GATE | E8: Specific conditions that reduce or remove the system's authority are written down, with the required response for each. | F8: No triggers exist. | G8: Triggers are informal ("we would pull it if something went badly wrong") or have no thresholds. | H8: Written triggers exist with measurable thresholds, and each trigger names the required response (restrict, pause, or revoke) and who executes it. | I8: As 2, and at least one trigger has been exercised in production or in a recorded drill within the last 12 months. | J8: 2 | K8: =IF(J8="","",CHOOSE(J8+1,"1 - Ad hoc","2 - Developing","3 - Defined","4 - Managed")) -> 3 - Defined | L8: Triggers: any duplicate payment; weekly sampling below 98% | M8: Authority Change Record AP-001, section E | N8: Run a demotion drill (owner: technical owner, by 31 May)
A9: 1.6 | B9: 1. Authorization and Decision Rights | C9: Enforced approval for high-consequence actions | E9: Actions above a defined consequence threshold require human approval, and the system enforces it. | F9: No approval step exists for any action. | G9: Approval is required by policy, but the system can execute without it. | H9: The system cannot execute defined high-consequence action classes without a recorded approval. | I9: As 2, and each approval record captures approver identity, timestamp, and the evidence the approver was shown. | J9: 3 | K9: =IF(J9="","",CHOOSE(J9+1,"1 - Ad hoc","2 - Developing","3 - Defined","4 - Managed")) -> 4 - Managed | L9: Every match approved by a clerk; approver, time and evidence captured | M9: Workflow audit table
A10: 2.1 | B10: 2. Data Governance | C10: Data source inventory | E10: Every data source the system can read from or write to is listed with an owner and a classification. | F10: No list exists. | G10: A list exists but is missing sources, owners, or classifications. | H10: A complete list exists, with a named owner and a data classification for every source. | I10: As 2, and the list is reconciled against actual access (from logs or access records) at least quarterly. | J10: 2 | K10: =IF(J10="","",CHOOSE(J10+1,"1 - Ad hoc","2 - Developing","3 - Defined","4 - Managed")) -> 3 - Defined | L10: ERP, PO, goods receipt and supplier master listed with owners | M10: Data inventory v2
A11: 2.2 | B11: 2. Data Governance | C11: Least-privilege access | E11: The system's credentials grant only the access it needs. | F11: The system uses shared, human, or administrator credentials. | G11: The system has dedicated credentials, but they grant access beyond the sources in 2.1 or do not separate read from write. | H11: Credentials are scoped to the sources in 2.1, with read and write permissions separated. | I11: As 2, and access is reviewed at least quarterly, with unused permissions removed and the removal recorded. | J11: 2 | K11: =IF(J11="","",CHOOSE(J11+1,"1 - Ad hoc","2 - Developing","3 - Defined","4 - Managed")) -> 3 - Defined | L11: Dedicated service identity, read and write separated | M11: Identity provider export
A12: 2.3 | B12: 2. Data Governance | C12: Sensitive data controls | E12: Personal, regulated, or confidential data is protected by technical controls, not only policy. | F12: No rules exist for sensitive data in this system. | G12: A policy exists, but no technical control enforces it. | H12: Technical controls (masking, filtering, or redaction) cover defined sensitive fields, and a test shows they work. | I12: As 2, and those tests run automatically before every release, and any failures are tracked as incidents. | J12: 2 | K12: =IF(J12="","",CHOOSE(J12+1,"1 - Ad hoc","2 - Developing","3 - Defined","4 - Managed")) -> 3 - Defined | L12: Bank details masked in prompts; test passes | M12: Masking test report
A13: 2.4 | B13: 2. Data Governance | C13: Provider data terms confirmed | E13: For every model and tool provider in the system's path, the team knows in writing whether the provider trains on, retains, or relocates enterprise data. | F13: Unknown for at least one provider. | G13: Based on marketing material or verbal assurance for at least one provider. | H13: Confirmed in a contract or data processing agreement for every provider in the path. | I13: As 2, and contracts require advance notice of changes to these terms, and the terms were reviewed within the last 12 months. | J13: 2 | K13: =IF(J13="","",CHOOSE(J13+1,"1 - Ad hoc","2 - Developing","3 - Defined","4 - Managed")) -> 3 - Defined | L13: Provider DPA confirms no training, 30-day retention | M13: Contract folder
A14: 2.5 | B14: 2. Data Governance | C14: Data residency and cross-border flows | E14: Where data travels is mapped for every market the system operates in. | F14: Data flows are not mapped. | G14: Mapped for the primary model only. | H14: Mapped for every component (model, retrieval store, logs, tools) in every market where the system operates. | I14: As 2, and legal or privacy has signed off each market's data flows, with a dated record. | J14: 1 | K14: =IF(J14="","",CHOOSE(J14+1,"1 - Ad hoc","2 - Developing","3 - Defined","4 - Managed")) -> 2 - Developing | L14: Model data flow mapped; logs and retrieval store not mapped | M14: Privacy review notes | N14: Map all components (owner: privacy, by 30 Apr)
A15: 3.1 | B15: 3. Evaluation and Testing | C15: Enterprise-owned evaluation set | E15: The team has its own test cases, built from its own tasks, not the vendor's demo set. | F15: No evaluation set exists; quality is judged from demos or anecdotes. | G15: An evaluation set exists, but it was supplied by the vendor, or it does not cover every action type. | H15: The enterprise owns an evaluation set with at least 20 cases per action type, drawn from real or realistic tasks, including documented edge cases and expected outcomes. | I15: As 2, and the set is refreshed with sampled production cases at least quarterly. | J15: 2 | K15: =IF(J15="","",CHOOSE(J15+1,"1 - Ad hoc","2 - Developing","3 - Defined","4 - Managed")) -> 3 - Defined | L15: 240 enterprise cases, including near-matches, partial deliveries and price variances | M15: Evaluation set v4
A16: 3.2 | B16: 3. Evaluation and Testing | C16: Pass thresholds set before testing | E16: Quality thresholds were written down before results were seen. | F16: No thresholds exist. | G16: Thresholds exist but were set after seeing results, or are not written down. | H16: Written thresholds exist for each action type, set before testing and approved by the authority owner (1.2). | I16: As 2, and thresholds are stricter for irreversible or high-consequence action types, with the reasoning documented. | J16: 2 | K16: =IF(J16="","",CHOOSE(J16+1,"1 - Ad hoc","2 - Developing","3 - Defined","4 - Managed")) -> 3 - Defined | L16: Thresholds approved by the AP controller before testing | M16: Test plan sign-off
A17: 3.3 | B17: 3. Evaluation and Testing | C17: Regression testing on every change | E17: Any change to the model version, prompts, tools, retrieval, or configuration triggers a re-run of the evaluation set. | F17: No regression testing happens. | G17: Testing happens for some changes, manually, at the team's discretion. | H17: Every change requires a regression run before release, and results are recorded. | I17: As 2, and the run is automated in the release pipeline, and a failed run blocks the release. | J17: 2 | K17: =IF(J17="","",CHOOSE(J17+1,"1 - Ad hoc","2 - Developing","3 - Defined","4 - Managed")) -> 3 - Defined | L17: Regression run required before every release | M17: Release checklist
A18: 3.4 | B18: 3. Evaluation and Testing | C18: Adversarial and safety testing | E18: The system is tested against misuse, not just normal use. | F18: No adversarial testing has been done. | G18: Informal attempts only, with no documented test cases. | H18: A documented test suite covers prompt injection, attempts to exceed the authority boundary in 1.1, and data leakage, and it was run before launch. | I18: As 2, and it runs on every release, and someone outside the build team has tested the system within the last 12 months. | J18: 1 | K18: =IF(J18="","",CHOOSE(J18+1,"1 - Ad hoc","2 - Developing","3 - Defined","4 - Managed")) -> 2 - Developing | L18: Informal injection attempts only; duplicate-payment scenario never tested | M18: None | N18: Build adversarial suite incl. duplicate payment (owner: tech lead, by 15 May)
A19: 3.5 | B19: 3. Evaluation and Testing | C19: Production quality sampling | E19: Live outputs are reviewed against the same standard used before launch. | F19: No production review happens. | G19: Occasional review with no defined sample size or cadence. | H19: A defined sample is reviewed on a defined cadence and scored with the pre-launch rubric. | I19: As 2, and results are trended over time and presented at the authority review (7.5). | J19: 2 | K19: =IF(J19="","",CHOOSE(J19+1,"1 - Ad hoc","2 - Developing","3 - Defined","4 - Managed")) -> 3 - Defined | L19: Weekly sample of 50 matches scored by clerks with the pre-launch rubric | M19: Sampling dashboard
A20: 4.1 | B20: 4. Observability and Audit | C20: Complete action trace | D20: GATE | E20: Every state-changing action is logged with: the trigger, the agent identity, the model and version, a reference to the inputs and retrieved context, every tool call, any approval, and the outcome. | F20: No action-level logging exists. | G20: Some of these fields are logged, or logging covers only some actions. | H20: All listed fields are captured for every state-changing action. | I20: As 2, and logs are tamper-evident or immutable, and retention meets the enterprise's written policy. | J20: 2 | K20: =IF(J20="","",CHOOSE(J20+1,"1 - Ad hoc","2 - Developing","3 - Defined","4 - Managed")) -> 3 - Defined | L20: All fields logged for every match flag | M20: Trace store
A21: 4.2 | B21: 4. Observability and Audit | C21: Reconstruction drill | E21: The team can reconstruct a specific past action end to end. | F21: Never attempted, or not possible. | G21: Possible, but it took engineers more than one business day. | H21: Done within one business day, and demonstrated within the last 6 months. | I21: Done within one hour using standard tooling, by someone outside the build team. | J21: 2 | K21: =IF(J21="","",CHOOSE(J21+1,"1 - Ad hoc","2 - Developing","3 - Defined","4 - Managed")) -> 3 - Defined | L21: Reconstruction done in 4 hours, February | M21: Drill record
A22: 4.3 | B22: 4. Observability and Audit | C22: Quality and drift alerting | E22: The system is monitored for quality, not only uptime. | F22: Only availability and latency are monitored. | G22: Quality metrics exist but nobody is alerted when they cross a threshold. | H22: Quality metrics have thresholds, and alerts go to a named owner. | I22: As 2, and input drift (change in the data the system sees) is also monitored, and alert routing has been tested. | J22: 1 | K22: =IF(J22="","",CHOOSE(J22+1,"1 - Ad hoc","2 - Developing","3 - Defined","4 - Managed")) -> 2 - Developing | L22: Agreement tracked; no alert threshold set | M22: Dashboard | N22: Set alert at 98.5% (owner: tech lead, by 30 Apr)
A23: 4.4 | B23: 4. Observability and Audit | C23: Human oversight metrics | E23: The team measures how human reviewers behave, not just how the system behaves. | F23: Approval rates, override rates, and review times are not tracked. | G23: Tracked, but not reviewed. | H23: Reviewed on a defined cadence by a named owner. | I23: As 2, and defined thresholds (for example, an approval rate above a set level, or review times below a set level) trigger a check on whether reviewers are still genuinely reviewing. | J23: 2 | K23: =IF(J23="","",CHOOSE(J23+1,"1 - Ad hoc","2 - Developing","3 - Defined","4 - Managed")) -> 3 - Defined | L23: Approval and override rates reviewed monthly | M23: Ops review minutes
A24: 4.5 | B24: 4. Observability and Audit | C24: Cost per completed action | E24: The team knows what one acceptable, completed action actually costs. | F24: Cost is not tracked for this system. | G24: Only cost per model call or per token is tracked. | H24: Fully loaded cost per accepted, completed action is tracked, including retries, human review time, and rework. | I24: As 2, and it is tracked against a written cost ceiling, with an alert when exceeded. | J24: 2 | K24: =IF(J24="","",CHOOSE(J24+1,"1 - Ad hoc","2 - Developing","3 - Defined","4 - Managed")) -> 3 - Defined | L24: True cost $0.40 per accepted match, including clerk review | M24: True Cost worksheet, March
A25: 5.1 | B25: 5. Safety and Guardrails | C25: Tested kill switch | D25: GATE | E25: Named people can stop all state-changing actions quickly, without a code deployment. | F25: No kill switch exists, or stopping the system requires a deployment. | G25: A kill switch exists, but it has never been tested. | H25: It was tested within the last 6 months, it stopped all state-changing actions within 15 minutes, and the people allowed to trigger it are named. | I25: As 2, and it was tested within the last 90 days, and it can be scoped (one action type, one market) as well as all-off. | J25: 1 | K25: =IF(J25="","",CHOOSE(J25+1,"1 - Ad hoc","2 - Developing","3 - Defined","4 - Managed")) -> 2 - Developing | L25: Kill switch exists; never tested | M25: Runbook | N25: Test kill switch (owner: technical owner, by 30 Apr)
A26: 5.2 | B26: 5. Safety and Guardrails | C26: Limits enforced outside the model | D26: GATE | E26: The authority boundary in 1.1 is enforced by systems the model cannot override. | F26: Limits rely only on prompt instructions. | G26: Some limits are enforced outside the model; others rely on the prompt. | H26: Every limit in 1.1 is enforced outside the model, at the tool layer, a policy engine, or the target system. | I26: As 2, and every attempted violation is logged and alerted to a named owner. | J26: 2 | K26: =IF(J26="","",CHOOSE(J26+1,"1 - Ad hoc","2 - Developing","3 - Defined","4 - Managed")) -> 3 - Defined | L26: Value limit enforced in the ERP integration, not the prompt | M26: Integration config
A27: 5.3 | B27: 5. Safety and Guardrails | C27: Reversibility classified | E27: Each action type is classified as reversible or irreversible, and irreversible actions are treated differently. | F27: Not assessed. | G27: Assessed informally, not written down. | H27: Every action type is classified in writing, and irreversible action types require approval (1.6) or have a documented compensating action. | I27: As 2, and the rollback or compensating procedure has been tested. | J27: 1 | K27: =IF(J27="","",CHOOSE(J27+1,"1 - Ad hoc","2 - Developing","3 - Defined","4 - Managed")) -> 2 - Developing | L27: Reversibility discussed, not written | M27: None | N27: Classify action types (owner: AP controller, by 30 Apr)
A28: 5.4 | B28: 5. Safety and Guardrails | C28: Blast-radius caps | E28: Business-level caps limit how much damage a fault can do before someone notices. | F28: No caps exist. | G28: Only infrastructure limits (rate limits, timeouts) exist. | H28: Business-level caps are enforced, such as records changed per hour or monetary value per day. | I28: As 2, and caps are formally reviewed every time the system's authority state changes. | J28: 2 | K28: =IF(J28="","",CHOOSE(J28+1,"1 - Ad hoc","2 - Developing","3 - Defined","4 - Managed")) -> 3 - Defined | L28: Cap: 300 flags per hour, $250,000 per day | M28: Integration config
A29: 5.5 | B29: 5. Safety and Guardrails | C29: Delegation controls | E29: Authority cannot grow by passing through other agents or tools. | F29: The agent can call other agents or tools without restriction. | G29: Delegation paths are documented but not enforced. | H29: Every delegation path is listed, and no path grants permissions beyond the authority boundary in 1.1. | I29: As 2, and the composed end-to-end behavior is covered by the evaluation set. A single agent that is technically prevented from calling other agents scores 3. | J29: 3 | K29: =IF(J29="","",CHOOSE(J29+1,"1 - Ad hoc","2 - Developing","3 - Defined","4 - Managed")) -> 4 - Managed | L29: Single agent, technically prevented from calling other agents | M29: Platform policy
A30: 6.1 | B30: 6. Reliability and Operations | C30: AI-specific incident playbook | E30: The team has a playbook for quality failures, not only outages. | F30: No playbook exists. | G30: Only a general IT incident playbook applies. | H30: An AI-specific playbook covers quality degradation as well as outage, with severity levels, a named owner, and steps to restrict or reset authority. | I30: As 2, and the playbook has been exercised within the last 12 months. | J30: 1 | K30: =IF(J30="","",CHOOSE(J30+1,"1 - Ad hoc","2 - Developing","3 - Defined","4 - Managed")) -> 2 - Developing | L30: General IT incident playbook only | M30: IT service desk | N30: Write AI quality playbook (owner: technical owner, by 31 May)
A31: 6.2 | B31: 6. Reliability and Operations | C31: Fallback path | E31: The business keeps working when the system is paused. | F31: No fallback; the process stops. | G31: A manual workaround exists but is not documented or staffed. | H31: A documented, staffed fallback exists and has been tested. | I31: As 2, and the switch to fallback happens automatically on defined triggers, and that switch has been tested. | J31: 2 | K31: =IF(J31="","",CHOOSE(J31+1,"1 - Ad hoc","2 - Developing","3 - Defined","4 - Managed")) -> 3 - Defined | L31: Clerks resume manual matching; tested in January | M31: Fallback test record
A32: 6.3 | B32: 6. Reliability and Operations | C32: Model and vendor change control | E32: Changes from the model or platform provider do not reach production untested. | F32: Provider changes are discovered after they affect behavior. | G32: The team subscribes to provider notices, but versions are not pinned. | H32: Model and platform versions are pinned, and upgrades pass regression testing (3.3) before rollout. | I32: As 2, and an alternative model or provider has been run against the evaluation set within the last 12 months. | J32: 2 | K32: =IF(J32="","",CHOOSE(J32+1,"1 - Ad hoc","2 - Developing","3 - Defined","4 - Managed")) -> 3 - Defined | L32: Model version pinned; upgrades pass regression | M32: Release checklist
A33: 6.4 | B33: 6. Reliability and Operations | C33: Downstream system dependencies | E33: Every system the agent writes to has defined failure behavior. | F33: Dependencies are not listed. | G33: Dependencies are listed, with no defined failure behavior. | H33: Each dependency has defined timeout, retry, and duplicate-action behavior, and it has been tested. | I33: As 2, and dependency health is monitored with alerts. | J33: 1 | K33: =IF(J33="","",CHOOSE(J33+1,"1 - Ad hoc","2 - Developing","3 - Defined","4 - Managed")) -> 2 - Developing | L33: Dependencies listed; duplicate-action behavior undefined | M33: Architecture page | N33: Define and test duplicate handling (owner: tech lead, by 15 May)
A34: 6.5 | B34: 6. Reliability and Operations | C34: Agreed service levels | E34: The business owner and the technical owner agree on what "working" means. | F34: No service levels exist. | G34: Availability targets only. | H34: Availability, latency, and quality targets are agreed in writing with the business owner. | I34: As 2, and performance is reported monthly, and any breach triggers a recorded review. | J34: 1 | K34: =IF(J34="","",CHOOSE(J34+1,"1 - Ad hoc","2 - Developing","3 - Defined","4 - Managed")) -> 2 - Developing | L34: Availability target only | M34: Service catalog | N34: Agree latency and quality targets (owner: AP controller, by 31 May)
A35: 7.1 | B35: 7. Ownership and Accountability | C35: Business owner | E35: A named person owns the business outcome and its economics. | F35: No business owner exists. | G35: A team is named, but no individual. | H35: A named individual owns the outcome, with a written success metric. | I35: As 2, and the metric is reported on a defined cadence and reviewed with that owner. | J35: 2 | K35: =IF(J35="","",CHOOSE(J35+1,"1 - Ad hoc","2 - Developing","3 - Defined","4 - Managed")) -> 3 - Defined | L35: AP controller owns cycle time and cost per invoice | M35: Initiative charter
A36: 7.2 | B36: 7. Ownership and Accountability | C36: Technical owner | E36: A named person owns operating and recovering the system. | F36: No technical owner exists. | G36: A team is named, but no individual. | H36: A named individual owns operations, with on-call coverage defined. | I36: As 2, and the on-call process has been tested, and runbooks were updated within the last 90 days. | J36: 2 | K36: =IF(J36="","",CHOOSE(J36+1,"1 - Ad hoc","2 - Developing","3 - Defined","4 - Managed")) -> 3 - Defined | L36: Named technical owner, on-call defined | M36: On-call rota
A37: 7.3 | B37: 7. Ownership and Accountability | C37: Risk owner and written acceptance | E37: A named person has accepted the residual risk of the system's current authority, in writing. | F37: No risk owner exists. | G37: Risk was discussed, but no one signed an acceptance. | H37: A named risk owner signed a written acceptance of residual risk for the current authority state. | I37: As 2, and acceptance is re-signed every time the authority state changes. | J37: 2 | K37: =IF(J37="","",CHOOSE(J37+1,"1 - Ad hoc","2 - Developing","3 - Defined","4 - Managed")) -> 3 - Defined | L37: Risk owner signed acceptance for Recommend | M37: Risk acceptance AP-R1
A38: 7.4 | B38: 7. Ownership and Accountability | C38: Agent identity and inventory | E38: The system is registered as a distinct, identifiable actor. | F38: The system is not in any inventory. | G38: Listed in an informal register, without a unique identity. | H38: Registered with a unique non-human identity, a named owner, and its current authority state. | I38: As 2, and the inventory is reconciled against agents actually running in production at least quarterly. | J38: 2 | K38: =IF(J38="","",CHOOSE(J38+1,"1 - Ad hoc","2 - Developing","3 - Defined","4 - Managed")) -> 3 - Defined | L38: Registered with a unique identity, owner and state | M38: Agent register
A39: 7.5 | B39: 7. Ownership and Accountability | C39: Scheduled authority review | E39: Authority is reviewed on a schedule, for demotion as well as promotion. | F39: No review happens after launch. | G39: Reviewed at launch only, or only when something goes wrong. | H39: Reviewed on a fixed cadence (at least quarterly for bounded or expanded autonomy), and the review considers both promotion and demotion. | I39: As 2, and each review records a decision (expand, maintain, constrain, pause, redesign, or exit) with conditions for the next review. | J39: 2 | K39: =IF(J39="","",CHOOSE(J39+1,"1 - Ad hoc","2 - Developing","3 - Defined","4 - Managed")) -> 3 - Defined | L39: Quarterly review, considers promotion and demotion | M39: Review calendar
A40: 7.6 | B40: 7. Ownership and Accountability | C40: Exit criteria | E40: The business conditions under which the initiative is redesigned, paused, or stopped are written down. | F40: No exit criteria exist. | G40: Discussed informally only. | H40: Written economic and risk conditions define when the initiative is redesigned, paused, or stopped. | I40: As 2, and the criteria were checked against current evidence at the most recent authority review. | J40: 2 | K40: =IF(J40="","",CHOOSE(J40+1,"1 - Ad hoc","2 - Developing","3 - Defined","4 - Managed")) -> 3 - Defined | L40: Stop line written at funding | M40: Stop Memo, part one

Sheet Summary
B2: Summary
B3: ='Start here'!C7 -> Invoice-matching agent, accounts payable (fictional)
B5: Category | C5: Criteria | D5: Scored | E5: Max | F5: Score | G5: Maturity level
B6: 1. Authorization and Decision Rights | C6: =COUNTIF(Scorecard!$B$4:$B$40,B6) -> 6 | D6: =SUMPRODUCT((Scorecard!$B$4:$B$40=B6)*ISNUMBER(Scorecard!$J$4:$J$40)) -> 6 | E6: =C6*3 -> 18 | F6: =SUMIF(Scorecard!$B$4:$B$40,B6,Scorecard!$J$4:$J$40) -> 13 | G6: =IF(D6<C6,"Incomplete",CHOOSE(ROUNDDOWN(F6/C6,0)+1,"1 - Ad hoc","2 - Developing","3 - Defined","4 - Managed")) -> 3 - Defined
B7: 2. Data Governance | C7: =COUNTIF(Scorecard!$B$4:$B$40,B7) -> 5 | D7: =SUMPRODUCT((Scorecard!$B$4:$B$40=B7)*ISNUMBER(Scorecard!$J$4:$J$40)) -> 5 | E7: =C7*3 -> 15 | F7: =SUMIF(Scorecard!$B$4:$B$40,B7,Scorecard!$J$4:$J$40) -> 9 | G7: =IF(D7<C7,"Incomplete",CHOOSE(ROUNDDOWN(F7/C7,0)+1,"1 - Ad hoc","2 - Developing","3 - Defined","4 - Managed")) -> 2 - Developing
B8: 3. Evaluation and Testing | C8: =COUNTIF(Scorecard!$B$4:$B$40,B8) -> 5 | D8: =SUMPRODUCT((Scorecard!$B$4:$B$40=B8)*ISNUMBER(Scorecard!$J$4:$J$40)) -> 5 | E8: =C8*3 -> 15 | F8: =SUMIF(Scorecard!$B$4:$B$40,B8,Scorecard!$J$4:$J$40) -> 9 | G8: =IF(D8<C8,"Incomplete",CHOOSE(ROUNDDOWN(F8/C8,0)+1,"1 - Ad hoc","2 - Developing","3 - Defined","4 - Managed")) -> 2 - Developing
B9: 4. Observability and Audit | C9: =COUNTIF(Scorecard!$B$4:$B$40,B9) -> 5 | D9: =SUMPRODUCT((Scorecard!$B$4:$B$40=B9)*ISNUMBER(Scorecard!$J$4:$J$40)) -> 5 | E9: =C9*3 -> 15 | F9: =SUMIF(Scorecard!$B$4:$B$40,B9,Scorecard!$J$4:$J$40) -> 9 | G9: =IF(D9<C9,"Incomplete",CHOOSE(ROUNDDOWN(F9/C9,0)+1,"1 - Ad hoc","2 - Developing","3 - Defined","4 - Managed")) -> 2 - Developing
B10: 5. Safety and Guardrails | C10: =COUNTIF(Scorecard!$B$4:$B$40,B10) -> 5 | D10: =SUMPRODUCT((Scorecard!$B$4:$B$40=B10)*ISNUMBER(Scorecard!$J$4:$J$40)) -> 5 | E10: =C10*3 -> 15 | F10: =SUMIF(Scorecard!$B$4:$B$40,B10,Scorecard!$J$4:$J$40) -> 9 | G10: =IF(D10<C10,"Incomplete",CHOOSE(ROUNDDOWN(F10/C10,0)+1,"1 - Ad hoc","2 - Developing","3 - Defined","4 - Managed")) -> 2 - Developing
B11: 6. Reliability and Operations | C11: =COUNTIF(Scorecard!$B$4:$B$40,B11) -> 5 | D11: =SUMPRODUCT((Scorecard!$B$4:$B$40=B11)*ISNUMBER(Scorecard!$J$4:$J$40)) -> 5 | E11: =C11*3 -> 15 | F11: =SUMIF(Scorecard!$B$4:$B$40,B11,Scorecard!$J$4:$J$40) -> 7 | G11: =IF(D11<C11,"Incomplete",CHOOSE(ROUNDDOWN(F11/C11,0)+1,"1 - Ad hoc","2 - Developing","3 - Defined","4 - Managed")) -> 2 - Developing
B12: 7. Ownership and Accountability | C12: =COUNTIF(Scorecard!$B$4:$B$40,B12) -> 6 | D12: =SUMPRODUCT((Scorecard!$B$4:$B$40=B12)*ISNUMBER(Scorecard!$J$4:$J$40)) -> 6 | E12: =C12*3 -> 18 | F12: =SUMIF(Scorecard!$B$4:$B$40,B12,Scorecard!$J$4:$J$40) -> 12 | G12: =IF(D12<C12,"Incomplete",CHOOSE(ROUNDDOWN(F12/C12,0)+1,"1 - Ad hoc","2 - Developing","3 - Defined","4 - Managed")) -> 3 - Defined
B13: Total | C13: =SUM(C6:C12) -> 37 | D13: =SUM(D6:D12) -> 37 | E13: =SUM(E6:E12) -> 111 | F13: =SUM(F6:F12) -> 68
B15: Gate criteria
B16: 1.1 Written authority boundary | F16: =IFERROR(IF(INDEX(Scorecard!$J$4:$J$40,MATCH("1.1",Scorecard!$A$4:$A$40,0))="","",INDEX(Scorecard!$J$4:$J$40,MATCH("1.1",Scorecard!$A$4:$A$40,0))),"") -> 2
B17: 1.2 Named authority owner | F17: =IFERROR(IF(INDEX(Scorecard!$J$4:$J$40,MATCH("1.2",Scorecard!$A$4:$A$40,0))="","",INDEX(Scorecard!$J$4:$J$40,MATCH("1.2",Scorecard!$A$4:$A$40,0))),"") -> 2
B18: 1.5 Demotion and revocation triggers | F18: =IFERROR(IF(INDEX(Scorecard!$J$4:$J$40,MATCH("1.5",Scorecard!$A$4:$A$40,0))="","",INDEX(Scorecard!$J$4:$J$40,MATCH("1.5",Scorecard!$A$4:$A$40,0))),"") -> 2
B19: 4.1 Complete action trace | F19: =IFERROR(IF(INDEX(Scorecard!$J$4:$J$40,MATCH("4.1",Scorecard!$A$4:$A$40,0))="","",INDEX(Scorecard!$J$4:$J$40,MATCH("4.1",Scorecard!$A$4:$A$40,0))),"") -> 2
B20: 5.1 Tested kill switch | F20: =IFERROR(IF(INDEX(Scorecard!$J$4:$J$40,MATCH("5.1",Scorecard!$A$4:$A$40,0))="","",INDEX(Scorecard!$J$4:$J$40,MATCH("5.1",Scorecard!$A$4:$A$40,0))),"") -> 1
B21: 5.2 Limits enforced outside the model | F21: =IFERROR(IF(INDEX(Scorecard!$J$4:$J$40,MATCH("5.2",Scorecard!$A$4:$A$40,0))="","",INDEX(Scorecard!$J$4:$J$40,MATCH("5.2",Scorecard!$A$4:$A$40,0))),"") -> 2
B23: Criteria scored (of 37) | C23: =COUNT(Scorecard!$J$4:$J$40) -> 37
B24: Total score (of 111) | C24: =SUM(Scorecard!$J$4:$J$40) -> 68
B25: Lowest gate score | C25: =IF(COUNT(F16:F21)<6,"",MIN(F16:F21)) -> 1
B26: Criteria scored 0 | C26: =COUNTIF(Scorecard!$J$4:$J$40,0) -> 0
B27: Band on total alone | C27: =IF(C24>=84,"Production-ready",IF(C24>=56,"Pilot-ready","Not ready")) -> Pilot-ready
B29: Readiness band | C29: =IF(C23<37,"Incomplete",IF(OR(C25=0,C24<56),"Not ready",IF(AND(C24>=95,C25=3,C26=0),"Expanded-ready",IF(AND(C24>=84,C25>=2,C26=0),"Production-ready","Pilot-ready")))) -> Pilot-ready
B30: Capped by a gate or a zero? | C30: =IF(C23<37,"",IF(C29="Expanded-ready","No",IF(C29<>C27,"Yes: the gates or a criterion at 0 hold the band below what the total alone would give","No"))) -> No
B31: Maximum authority state | C31: =IF(C29="Incomplete","Score all 37 criteria first",INDEX(Reference!$D$12:$D$15,MATCH(C29,Reference!$A$12:$A$15,0))) -> Recommend, or act with approval in a limited scope
B32: Authority the system holds today | C32: =IF(HeldState="","Enter it on Start here",HeldState) -> Recommend
B33: Gap check | C33: =IF(HeldState="","",IF(C29="Incomplete","",IF(INDEX(Reference!$B$4:$B$8,MATCH(HeldState,Reference!$A$4:$A$8,0))>INDEX(Reference!$E$12:$E$15,MATCH(C29,Reference!$A$12:$A$15,0)),"GAP: the system holds more authority than its band allows. The authority owner restricts it now or accepts the gap in writing within one week.","Within band: the system holds no more authority than its evidence allows."))) -> Within band: the system holds no more authority than its evidence allows.
B34: Next steps | C34: =IF(C29="Incomplete","",INDEX(Reference!$F$12:$F$15,MATCH(C29,Reference!$A$12:$A$15,0))) -> Run a bounded pilot: recommend or act with approval in one market, one action type, capped volume. Build the missing evidence, especially 3.5, 4.4 and 4.5. Lift every gate to 2. Re-score before any request to expand scope.
B36: A high total does not cover a gap in a gate. Strong evidence in five places does not make up for missing evidence in the sixth.

Sheet Reference
A1: Reference tables used by the formulas. Do not edit.
A3: Authority state | B3: Rank | C3: What the system may do
A4: Observe | B4: 1 | C4: Watch and report. No output reaches a decision.
A5: Recommend | B5: 2 | C5: Suggest. A person decides and acts.
A6: Act with approval | B6: 3 | C6: Prepare the action. A person approves each one before it happens.
A7: Bounded autonomy | B7: 4 | C7: Act alone inside written limits, with every action traced and reversible where possible.
A8: Expanded autonomy | B8: 5 | C8: Act alone across a wider scope, earned by sustained evidence at the bounded level.
A11: Band | B11: Total score | C11: Gate condition | D11: Maximum authority state | E11: Allowed rank | F11: Next steps
A12: Not ready | B12: 0 to 55 | C12: Or any gate scored 0 | D12: Observe only | E12: 1 | F12: Run in observe mode only. Fix every gate scored 0 first, then name the authority owner (1.2), business owner (7.1) and risk owner (7.3). Re-score in 4 to 8 weeks.
A13: Pilot-ready | B13: 56 to 83 | C13: Every gate at 1 or higher | D13: Recommend, or act with approval in a limited scope | E13: 3 | F13: Run a bounded pilot: recommend or act with approval in one market, one action type, capped volume. Build the missing evidence, especially 3.5, 4.4 and 4.5. Lift every gate to 2. Re-score before any request to expand scope.
A14: Production-ready | B14: 84 to 111 | C14: Every gate at 2 or higher, and no criterion at 0 | D14: Bounded autonomy within the written limits in 1.1 | E14: 4 | F14: Bounded autonomy within the written limits is defensible. Hold the scheduled authority review (7.5). Treat the score as perishable. Re-score at least quarterly and at every authority change.
A15: Expanded-ready | B15: 95 to 111 | C15: Every gate at 3, and no criterion at 0 | D15: Expanded autonomy, with a 60-day sunset on every grant | E15: 5 | F15: Expanded autonomy is defensible for the action types where the evidence exists. Record each grant on an Authority Change Record with a 60-day sunset and re-score before every renewal.
A17: Expanded-ready is the top of the Production-ready range with a stricter gate condition, not a separate range.
